LICENSE
README.md
setup.cfg
setup.py
eereid/__init__.py
eereid/gag.py
eereid/ghost.py
eereid/importhelper.py
eereid/rename_all.py
eereid/tools.py
eereid.egg-info/PKG-INFO
eereid.egg-info/SOURCES.txt
eereid.egg-info/dependency_links.txt
eereid.egg-info/top_level.txt
eereid/datasets/__init__.py
eereid/datasets/atrw.py
eereid/datasets/cifar.py
eereid/datasets/cuhk03.py
eereid/datasets/dataset.py
eereid/datasets/downloadable.py
eereid/datasets/fmnist.py
eereid/datasets/from_folder.py
eereid/datasets/from_numpy.py
eereid/datasets/load_data.py
eereid/datasets/market1501.py
eereid/datasets/metal.py
eereid/datasets/mnist.py
eereid/datasets/pallet32965.py
eereid/datasets/pallet502.py
eereid/datasets/palletlight.py
eereid/distances/__init__.py
eereid/distances/chisquare.py
eereid/distances/cosine_similarity.py
eereid/distances/custom_distance.py
eereid/distances/distance.py
eereid/distances/euclidean.py
eereid/distances/lN.py
eereid/distances/mahalanobis.py
eereid/distances/manhattan.py
eereid/losses/__init__.py
eereid/losses/contrastive.py
eereid/losses/custom_loss.py
eereid/losses/extended_triplet.py
eereid/losses/loss.py
eereid/losses/quadruplet.py
eereid/losses/ringloss.py
eereid/losses/triplet.py
eereid/models/__init__.py
eereid/models/advanced_graph.py
eereid/models/custom_model.py
eereid/models/load_model.py
eereid/models/model.py
eereid/models/modelzoo.py
eereid/models/null.py
eereid/models/simple_conv.py
eereid/models/simple_dense.py
eereid/models/simple_graph.py
eereid/models/wrapmodel.py
eereid/modifier/__init__.py
eereid/modifier/crossval.py
eereid/modifier/modifier.py
eereid/modifier/mods.py
eereid/modifier/pretrain.py
eereid/modifier/repeated.py
eereid/novelty/__init__.py
eereid/novelty/distance.py
eereid/novelty/knn.py
eereid/novelty/novelty.py
eereid/novelty/pyod_wrapper.py
eereid/novelty/sod.py
eereid/prepros/__init__.py
eereid/prepros/add_color.py
eereid/prepros/apply_func.py
eereid/prepros/blackwhite.py
eereid/prepros/classsample.py
eereid/prepros/crop.py
eereid/prepros/featurebagging.py
eereid/prepros/flatten.py
eereid/prepros/flips.py
eereid/prepros/grapho.py
