Metadata-Version: 2.1
Name: eereid
Version: 0.1.1
Summary: Python module providing tools for training and evaluating re-identification models.
Home-page: https://github.com/psorus/eereid
Download-URL: https://github.com/psorus/eereid/archive/v_01.tar.gz
Author: Simon Klüttermann, Jérôme Rutinowski
Author-email: Simon.Kluettermann@cs.tu-dortmund.de
License: apache-2.0
Keywords: Re-ID,Reidentification,Contrastive Learning,Metric Learning,Machine Learning,ML
Platform: UNKNOWN
Classifier: Development Status :: 3 - Alpha
Classifier: Intended Audience :: Science/Research
Classifier: Topic :: Software Development :: Build Tools
Classifier: License :: OSI Approved :: Apache Software License
Classifier: Programming Language :: Python :: 3
Classifier: Programming Language :: Python :: 3.6
Classifier: Programming Language :: Python :: 3.7
Classifier: Programming Language :: Python :: 3.8
Classifier: Programming Language :: Python :: 3.9
Classifier: Programming Language :: Python :: 3.10
License-File: LICENSE
